pydevd_plugins/__init__.py
pydevd_plugins/extensions/__init__.py
pydevd_plugins/extensions/pydevd_plugin_odoo.py
pydevd_odoo-1.2.2.dist-info/LICENSE
pydevd_odoo-1.2.2.dist-info/METADATA
pydevd_odoo-1.2.2.dist-info/WHEEL
pydevd_odoo-1.2.2.dist-info/top_level.txt
pydevd_odoo-1.2.2.dist-info/RECORD
