Metadata-Version: 2.1
Name: pydevd-odoo
Version: 1.2.2
Summary: PyDev.Debugger plugin for Odoo
Author-email: Trinh Anh Ngoc <atw1990@gmail.com>
License: MIT
Project-URL: Homepage, https://github.com/odoo-ide/pydevd-odoo
Project-URL: Bug Tracker, https://github.com/odoo-ide/pydevd-odoo/issues
License-File: LICENSE
